quantconnect_mcp/__init__.py
quantconnect_mcp/main.py
quantconnect_mcp/src/__init__.py
quantconnect_mcp/src/cli.py
quantconnect_mcp/src/server.py
quantconnect_mcp/src/utils.py
quantconnect_mcp/src/auth/__init__.py
quantconnect_mcp/src/auth/quantconnect_auth.py
quantconnect_mcp/src/resources/__init__.py
quantconnect_mcp/src/tools/__init__.py
quantconnect_mcp/src/tools/auth_tools.py
quantconnect_mcp/src/tools/backtest_tools.py
quantconnect_mcp/src/tools/file_tools.py
quantconnect_mcp/src/tools/live_tools.py
quantconnect_mcp/src/tools/optimization_tools.py
quantconnect_mcp/src/tools/project_tools.py
quantconnect_mcp-0.3.5.dist-info/licenses/LICENSE
quantconnect_mcp-0.3.5.dist-info/METADATA
quantconnect_mcp-0.3.5.dist-info/WHEEL
quantconnect_mcp-0.3.5.dist-info/entry_points.txt
quantconnect_mcp-0.3.5.dist-info/top_level.txt
quantconnect_mcp-0.3.5.dist-info/RECORD
