Metadata-Version: 2.4
Name: quantconnect-mcp
Version: 0.3.5
Summary: QuantConnect platform integration with AI assistants for algorithmic trading project management, backtesting, and API access through MCP
Requires-Python: >=3.12
License-File: LICENSE
Requires-Dist: arch>=7.2.0
Requires-Dist: fastmcp==2.11.2
Requires-Dist: httpx>=0.28.1
Requires-Dist: matplotlib>=3.10.3
Requires-Dist: numpy<2.0.0,>=1.24.0
Requires-Dist: pandas>=2.3.0
Requires-Dist: psutil>=7.0.0
Requires-Dist: pytest-asyncio>=1.0.0
Requires-Dist: scikit-learn>=1.7.0
Requires-Dist: scipy>=1.15.3
Requires-Dist: seaborn>=0.13.2
Requires-Dist: statsmodels>=0.14.4
Requires-Dist: quantconnect-lean
Requires-Dist: quantconnect>=0.1.0
Dynamic: license-file
